CHANGELOG.md
CITATION.cff
CONTRIBUTING.rst
LICENSE.txt
MANIFEST.in
README.rst
RELEASE_PROCESS.rst
VERSION
mypy.ini
setup.cfg
setup.py
LFake.egg-info/PKG-INFO
LFake.egg-info/SOURCES.txt
LFake.egg-info/dependency_links.txt
LFake.egg-info/entry_points.txt
LFake.egg-info/requires.txt
LFake.egg-info/top_level.txt
LFake.egg-info/zip-safe
lfake/__init__.py
lfake/__main__.py
lfake/cli.py
lfake/config.py
lfake/documentor.py
lfake/exceptions.py
lfake/factory.py
lfake/generator.py
lfake/proxy.py
lfake/py.typed
lfake/typing.py
lfake/contrib/__init__.py
lfake/contrib/pytest/__init__.py
lfake/contrib/pytest/plugin.py
lfake/decode/__init__.py
lfake/decode/codes.py
lfake/providers/__init__.py
lfake/providers/address/__init__.py
lfake/providers/address/az_AZ/__init__.py
lfake/providers/address/bn_BD/__init__.py
lfake/providers/address/cs_CZ/__init__.py
lfake/providers/address/da_DK/__init__.py
lfake/providers/address/de/__init__.py
lfake/providers/address/de_AT/__init__.py
lfake/providers/address/de_CH/__init__.py
lfake/providers/address/de_DE/__init__.py
lfake/providers/address/el_GR/__init__.py
lfake/providers/address/en/__init__.py
lfake/providers/address/en_AU/__init__.py
lfake/providers/address/en_CA/__init__.py
lfake/providers/address/en_GB/__init__.py
lfake/providers/address/en_IE/__init__.py
lfake/providers/address/en_IN/__init__.py
lfake/providers/address/en_NZ/__init__.py
lfake/providers/address/en_PH/__init__.py
lfake/providers/address/en_US/__init__.py
lfake/providers/address/es/__init__.py
lfake/providers/address/es_AR/__init__.py
lfake/providers/address/es_CL/__init__.py
lfake/providers/address/es_CO/__init__.py
lfake/providers/address/es_ES/__init__.py
lfake/providers/address/es_MX/__init__.py
lfake/providers/address/fa_IR/__init__.py
lfake/providers/address/fi_FI/__init__.py
lfake/providers/address/fil_PH/__init__.py
lfake/providers/address/fr_CA/__init__.py
lfake/providers/address/fr_CH/__init__.py
lfake/providers/address/fr_FR/__init__.py
lfake/providers/address/he_IL/__init__.py
lfake/providers/address/hi_IN/__init__.py
lfake/providers/address/hr_HR/__init__.py
lfake/providers/address/hu_HU/__init__.py
lfake/providers/address/hy_AM/__init__.py
